{
  "law_id": "2528",
  "law_name": "最高人民法院关于适用《中华人民共和国民事诉讼法》执行程序若干问题的解释",
  "annotations": {
    "第一条": "执行管辖证明",
    "第二条": "重复立案处理",
    "第三条": "执行管辖异议",
    "第四条": "保全财产移交",
    "第五条": "执行行为异议",
    "第六条": "复议申请形式",
    "第七条": "复议材料提交",
    "第八条": "复议审查期限",
    "第九条": "异议复议期间执行",
    "第十条": "限期执行或变更执行法院",
    "第十一条": "督促执行令",
    "第十二条": "限期执行未完成处理",
    "第十三条": "六个月期间计算",
    "第十四条": "案外人异议",
    "第十五条": "案外人异议审查期间处分限制",
    "第十六条": "案外人异议之诉期间处分限制",
    "第十七条": "参与分配程序",
    "第十八条": "分配方案异议处理",
    "第十九条": "申请执行时效中止",
    "第二十条": "申请执行时效中断",
    "第二十一条": "不作为义务时效起算",
    "第二十二条": "立即执行通知",
    "第二十三条": "限制出境申请",
    "第二十四条": "限制出境对象",
    "第二十五条": "限制出境解除",
    "第二十六条": "公布失信信息",
    "第二十七条": "新旧司法解释适用"
  },
  "chapter_annotations": {}
}